{
  "id": "Postman",
  "label": "Postman",
  "version": "0.1.0",
  "description": "Arcade.dev tools for interacting with Postman",
  "metadata": {
    "category": "development",
    "iconUrl": "https://design-system.arcade.dev/icons/postman.svg",
    "isBYOC": false,
    "isPro": false,
    "type": "arcade",
    "docsLink": "https://docs.arcade.dev/en/resources/integrations/development/postman",
    "isComingSoon": false,
    "isHidden": false
  },
  "auth": null,
  "tools": [
    {
      "name": "CreateCollectionFolder",
      "qualifiedName": "Postman.CreateCollectionFolder",
      "fullyQualifiedName": "Postman.CreateCollectionFolder@0.1.0",
      "description": "Add a folder to a collection, optionally nested inside an existing folder.",
      "parameters": [
        {
          "name": "collection_id",
          "type": "string",
          "required": true,
          "description": "The collection id or uid to add the folder to.",
          "enum": null,
          "inferrable": true
        },
        {
          "name": "name",
          "type": "string",
          "required": true,
          "description": "Name for the new folder.",
          "enum": null,
          "inferrable": true
        },
        {
          "name": "description",
          "type": "string",
          "required": false,
          "description": "Description for the folder. Leave empty to omit.",
          "enum": null,
          "inferrable": true
        },
        {
          "name": "parent_folder_id",
          "type": "string",
          "required": false,
          "description": "Id of a folder to nest this folder inside. Leave empty to add at the top level.",
          "enum": null,
          "inferrable": true
        }
      ],
      "auth": null,
      "secrets": [
        "POSTMAN_API_KEY"
      ],
      "secretsInfo": [
        {
          "name": "POSTMAN_API_KEY",
          "type": "api_key"
        }
      ],
      "output": {
        "type": "json",
        "description": "The newly created folder."
      },
      "documentationChunks": [],
      "codeExample": {
        "toolName": "Postman.CreateCollectionFolder",
        "parameters": {
          "collection_id": {
            "value": "12345678-abcd-1234-efgh-abcdef123456",
            "type": "string",
            "required": true
          },
          "name": {
            "value": "Authentication Endpoints",
            "type": "string",
            "required": true
          },
          "description": {
            "value": "Contains all authentication-related API requests including login, logout, and token refresh.",
            "type": "string",
            "required": false
          },
          "parent_folder_id": {
            "value": "98765432-wxyz-5678-ijkl-wxyzab987654",
            "type": "string",
            "required": false
          }
        },
        "requiresAuth": false,
        "tabLabel": "Call the Tool"
      },
      "metadata": {
        "classification": {
          "serviceDomains": []
        },
        "behavior": {
          "operations": [
            "create"
          ],
          "readOnly": false,
          "destructive": false,
          "idempotent": false,
          "openWorld": true
        },
        "extras": null
      }
    },
    {
      "name": "CreateCollectionRequest",
      "qualifiedName": "Postman.CreateCollectionRequest",
      "fullyQualifiedName": "Postman.CreateCollectionRequest@0.1.0",
      "description": "Add a request to a collection, optionally inside a folder.",
      "parameters": [
        {
          "name": "collection_id",
          "type": "string",
          "required": true,
          "description": "The collection id or uid to add the request to.",
          "enum": null,
          "inferrable": true
        },
        {
          "name": "name",
          "type": "string",
          "required": true,
          "description": "Name for the new request.",
          "enum": null,
          "inferrable": true
        },
        {
          "name": "http_method",
          "type": "string",
          "required": true,
          "description": "HTTP method for the request.",
          "enum": [
            "GET",
            "POST",
            "PUT",
            "PATCH",
            "DELETE",
            "HEAD",
            "OPTIONS"
          ],
          "inferrable": true
        },
        {
          "name": "url",
          "type": "string",
          "required": true,
          "description": "Request URL.",
          "enum": null,
          "inferrable": true
        },
        {
          "name": "folder_id",
          "type": "string",
          "required": false,
          "description": "Id of a folder to place the request in. Leave empty to add at the top level.",
          "enum": null,
          "inferrable": true
        }
      ],
      "auth": null,
      "secrets": [
        "POSTMAN_API_KEY"
      ],
      "secretsInfo": [
        {
          "name": "POSTMAN_API_KEY",
          "type": "api_key"
        }
      ],
      "output": {
        "type": "json",
        "description": "The newly created request."
      },
      "documentationChunks": [],
      "codeExample": {
        "toolName": "Postman.CreateCollectionRequest",
        "parameters": {
          "collection_id": {
            "value": "12345678-abcd-1234-efgh-0987654321ab",
            "type": "string",
            "required": true
          },
          "name": {
            "value": "Get User Profile",
            "type": "string",
            "required": true
          },
          "http_method": {
            "value": "GET",
            "type": "string",
            "required": true
          },
          "url": {
            "value": "https://api.example.com/v1/users/{{userId}}/profile",
            "type": "string",
            "required": true
          },
          "folder_id": {
            "value": "f1a2b3c4-d5e6-7890-abcd-ef1234567890",
            "type": "string",
            "required": false
          }
        },
        "requiresAuth": false,
        "tabLabel": "Call the Tool"
      },
      "metadata": {
        "classification": {
          "serviceDomains": []
        },
        "behavior": {
          "operations": [
            "create"
          ],
          "readOnly": false,
          "destructive": false,
          "idempotent": false,
          "openWorld": true
        },
        "extras": null
      }
    },
    {
      "name": "CreateMock",
      "qualifiedName": "Postman.CreateMock",
      "fullyQualifiedName": "Postman.CreateMock@0.1.0",
      "description": "Create a mock server from a collection so a client can call its simulated endpoints.",
      "parameters": [
        {
          "name": "collection_id",
          "type": "string",
          "required": true,
          "description": "Id or uid of the collection the mock server simulates. Prefer the uid: it avoids a resolving lookup (useful in batches) and reliably addresses a teammate-shared collection, whose bare id can be rejected.",
          "enum": null,
          "inferrable": true
        },
        {
          "name": "name",
          "type": "string",
          "required": false,
          "description": "Name for the mock server. Leave empty to let Postman name it.",
          "enum": null,
          "inferrable": true
        },
        {
          "name": "environment_id",
          "type": "string",
          "required": false,
          "description": "Id or uid of an environment to bind to the mock. Prefer the uid for a teammate-shared environment, whose bare id can be rejected. Leave empty for none.",
          "enum": null,
          "inferrable": true
        },
        {
          "name": "workspace_id",
          "type": "string",
          "required": false,
          "description": "Workspace to create the mock in. Leave empty to use your personal (default) workspace; passing it avoids a default-workspace lookup, useful when creating many in a batch.",
          "enum": null,
          "inferrable": true
        },
        {
          "name": "private",
          "type": "boolean",
          "required": false,
          "description": "Create the mock as private (true), so only requests carrying a valid Postman API key reach it, or public (false), reachable by anyone with the URL. Defaults to true; a public mock exposes the collection's saved example responses to anyone with the URL.",
          "enum": null,
          "inferrable": true
        }
      ],
      "auth": null,
      "secrets": [
        "POSTMAN_API_KEY"
      ],
      "secretsInfo": [
        {
          "name": "POSTMAN_API_KEY",
          "type": "api_key"
        }
      ],
      "output": {
        "type": "json",
        "description": "The newly created mock server and its public URL."
      },
      "documentationChunks": [],
      "codeExample": {
        "toolName": "Postman.CreateMock",
        "parameters": {
          "collection_id": {
            "value": "12345678-ab12cd34-ef56-7890-gh12-ij3456klmn78",
            "type": "string",
            "required": true
          },
          "name": {
            "value": "Payments API Mock Server",
            "type": "string",
            "required": false
          },
          "environment_id": {
            "value": "12345678-bc98ef76-5432-10dc-ba98-76fedcba5432",
            "type": "string",
            "required": false
          },
          "workspace_id": {
            "value": "a1b2c3d4-e5f6-7890-abcd-ef1234567890",
            "type": "string",
            "required": false
          },
          "private": {
            "value": true,
            "type": "boolean",
            "required": false
          }
        },
        "requiresAuth": false,
        "tabLabel": "Call the Tool"
      },
      "metadata": {
        "classification": {
          "serviceDomains": []
        },
        "behavior": {
          "operations": [
            "create"
          ],
          "readOnly": false,
          "destructive": false,
          "idempotent": false,
          "openWorld": true
        },
        "extras": null
      }
    },
    {
      "name": "CreateMonitor",
      "qualifiedName": "Postman.CreateMonitor",
      "fullyQualifiedName": "Postman.CreateMonitor@0.1.0",
      "description": "Create a monitor that runs a collection on a schedule to watch an API's health.",
      "parameters": [
        {
          "name": "collection_id",
          "type": "string",
          "required": true,
          "description": "Id or uid of the collection the monitor runs. Prefer the uid: it avoids a resolving lookup (useful in batches) and reliably addresses a teammate-shared collection, whose bare id can be rejected.",
          "enum": null,
          "inferrable": true
        },
        {
          "name": "name",
          "type": "string",
          "required": true,
          "description": "Name for the monitor.",
          "enum": null,
          "inferrable": true
        },
        {
          "name": "cron",
          "type": "string",
          "required": false,
          "description": "Cron expression for the run schedule (standard 5-field cron). Defaults to '0 0 * * *' (daily at midnight).",
          "enum": null,
          "inferrable": true
        },
        {
          "name": "timezone",
          "type": "string",
          "required": false,
          "description": "IANA timezone name for the schedule (e.g. America/New_York). Defaults to Etc/UTC.",
          "enum": null,
          "inferrable": true
        },
        {
          "name": "environment_id",
          "type": "string",
          "required": false,
          "description": "Id or uid of an environment to run the monitor against. Prefer the uid for a teammate-shared environment, whose bare id can be rejected. Leave empty for none.",
          "enum": null,
          "inferrable": true
        },
        {
          "name": "workspace_id",
          "type": "string",
          "required": false,
          "description": "Workspace to create the monitor in. Leave empty to use your personal (default) workspace; passing it avoids a default-workspace lookup, useful when creating many in a batch.",
          "enum": null,
          "inferrable": true
        }
      ],
      "auth": null,
      "secrets": [
        "POSTMAN_API_KEY"
      ],
      "secretsInfo": [
        {
          "name": "POSTMAN_API_KEY",
          "type": "api_key"
        }
      ],
      "output": {
        "type": "json",
        "description": "The newly created monitor and its schedule."
      },
      "documentationChunks": [],
      "codeExample": {
        "toolName": "Postman.CreateMonitor",
        "parameters": {
          "collection_id": {
            "value": "12345678-ab12cd34-ef56-7890-gh12-ij3456klmn78",
            "type": "string",
            "required": true
          },
          "name": {
            "value": "Production API Health Monitor",
            "type": "string",
            "required": true
          },
          "cron": {
            "value": "0 9 * * 1-5",
            "type": "string",
            "required": false
          },
          "timezone": {
            "value": "America/New_York",
            "type": "string",
            "required": false
          },
          "environment_id": {
            "value": "12345678-bc98ef76-54dc-3210-ba12-cd9876efab54",
            "type": "string",
            "required": false
          },
          "workspace_id": {
            "value": "a1b2c3d4-e5f6-7890-abcd-ef1234567890",
            "type": "string",
            "required": false
          }
        },
        "requiresAuth": false,
        "tabLabel": "Call the Tool"
      },
      "metadata": {
        "classification": {
          "serviceDomains": []
        },
        "behavior": {
          "operations": [
            "create"
          ],
          "readOnly": false,
          "destructive": false,
          "idempotent": false,
          "openWorld": true
        },
        "extras": null
      }
    },
    {
      "name": "DeleteCollection",
      "qualifiedName": "Postman.DeleteCollection",
      "fullyQualifiedName": "Postman.DeleteCollection@0.1.0",
      "description": "Permanently delete a collection. This cannot be undone.",
      "parameters": [
        {
          "name": "collection_id",
          "type": "string",
          "required": true,
          "description": "The collection id or uid to delete.",
          "enum": null,
          "inferrable": true
        }
      ],
      "auth": null,
      "secrets": [
        "POSTMAN_API_KEY"
      ],
      "secretsInfo": [
        {
          "name": "POSTMAN_API_KEY",
          "type": "api_key"
        }
      ],
      "output": {
        "type": "json",
        "description": "Confirmation that the collection was deleted."
      },
      "documentationChunks": [],
      "codeExample": {
        "toolName": "Postman.DeleteCollection",
        "parameters": {
          "collection_id": {
            "value": "12345678-abcd-efgh-ijkl-1234567890ab",
            "type": "string",
            "required": true
          }
        },
        "requiresAuth": false,
        "tabLabel": "Call the Tool"
      },
      "metadata": {
        "classification": {
          "serviceDomains": []
        },
        "behavior": {
          "operations": [
            "delete"
          ],
          "readOnly": false,
          "destructive": true,
          "idempotent": true,
          "openWorld": true
        },
        "extras": null
      }
    },
    {
      "name": "DeleteCollectionItem",
      "qualifiedName": "Postman.DeleteCollectionItem",
      "fullyQualifiedName": "Postman.DeleteCollectionItem@0.1.0",
      "description": "Delete a folder or request from a collection. This cannot be undone.\n\nDeleting a folder also removes the requests it contains.",
      "parameters": [
        {
          "name": "collection_id",
          "type": "string",
          "required": true,
          "description": "The collection id or uid containing the item.",
          "enum": null,
          "inferrable": true
        },
        {
          "name": "item_id",
          "type": "string",
          "required": true,
          "description": "Id of the folder or request to delete.",
          "enum": null,
          "inferrable": true
        },
        {
          "name": "item_type",
          "type": "string",
          "required": true,
          "description": "Whether the item is a folder or a request.",
          "enum": [
            "folder",
            "request"
          ],
          "inferrable": true
        }
      ],
      "auth": null,
      "secrets": [
        "POSTMAN_API_KEY"
      ],
      "secretsInfo": [
        {
          "name": "POSTMAN_API_KEY",
          "type": "api_key"
        }
      ],
      "output": {
        "type": "json",
        "description": "Confirmation that the folder or request was deleted."
      },
      "documentationChunks": [],
      "codeExample": {
        "toolName": "Postman.DeleteCollectionItem",
        "parameters": {
          "collection_id": {
            "value": "12345678-abcd-efgh-ijkl-1234567890ab",
            "type": "string",
            "required": true
          },
          "item_id": {
            "value": "a1b2c3d4-e5f6-7890-abcd-ef1234567890",
            "type": "string",
            "required": true
          },
          "item_type": {
            "value": "folder",
            "type": "string",
            "required": true
          }
        },
        "requiresAuth": false,
        "tabLabel": "Call the Tool"
      },
      "metadata": {
        "classification": {
          "serviceDomains": []
        },
        "behavior": {
          "operations": [
            "delete"
          ],
          "readOnly": false,
          "destructive": true,
          "idempotent": true,
          "openWorld": true
        },
        "extras": null
      }
    },
    {
      "name": "DeleteEnvironment",
      "qualifiedName": "Postman.DeleteEnvironment",
      "fullyQualifiedName": "Postman.DeleteEnvironment@0.1.0",
      "description": "Permanently delete an environment. This cannot be undone.",
      "parameters": [
        {
          "name": "environment_id",
          "type": "string",
          "required": true,
          "description": "The environment id or uid to delete.",
          "enum": null,
          "inferrable": true
        }
      ],
      "auth": null,
      "secrets": [
        "POSTMAN_API_KEY"
      ],
      "secretsInfo": [
        {
          "name": "POSTMAN_API_KEY",
          "type": "api_key"
        }
      ],
      "output": {
        "type": "json",
        "description": "Confirmation that the environment was deleted."
      },
      "documentationChunks": [],
      "codeExample": {
        "toolName": "Postman.DeleteEnvironment",
        "parameters": {
          "environment_id": {
            "value": "5daabc50-8451-43f6-922d-96b403b4f28e",
            "type": "string",
            "required": true
          }
        },
        "requiresAuth": false,
        "tabLabel": "Call the Tool"
      },
      "metadata": {
        "classification": {
          "serviceDomains": []
        },
        "behavior": {
          "operations": [
            "delete"
          ],
          "readOnly": false,
          "destructive": true,
          "idempotent": true,
          "openWorld": true
        },
        "extras": null
      }
    },
    {
      "name": "DeleteMock",
      "qualifiedName": "Postman.DeleteMock",
      "fullyQualifiedName": "Postman.DeleteMock@0.1.0",
      "description": "Permanently delete a mock server. This cannot be undone.",
      "parameters": [
        {
          "name": "mock_id",
          "type": "string",
          "required": true,
          "description": "The mock server id to delete.",
          "enum": null,
          "inferrable": true
        }
      ],
      "auth": null,
      "secrets": [
        "POSTMAN_API_KEY"
      ],
      "secretsInfo": [
        {
          "name": "POSTMAN_API_KEY",
          "type": "api_key"
        }
      ],
      "output": {
        "type": "json",
        "description": "Confirmation that the mock server was deleted."
      },
      "documentationChunks": [],
      "codeExample": {
        "toolName": "Postman.DeleteMock",
        "parameters": {
          "mock_id": {
            "value": "a1b2c3d4-e5f6-7890-abcd-ef1234567890",
            "type": "string",
            "required": true
          }
        },
        "requiresAuth": false,
        "tabLabel": "Call the Tool"
      },
      "metadata": {
        "classification": {
          "serviceDomains": []
        },
        "behavior": {
          "operations": [
            "delete"
          ],
          "readOnly": false,
          "destructive": true,
          "idempotent": true,
          "openWorld": true
        },
        "extras": null
      }
    },
    {
      "name": "DeleteMonitor",
      "qualifiedName": "Postman.DeleteMonitor",
      "fullyQualifiedName": "Postman.DeleteMonitor@0.1.0",
      "description": "Permanently delete a monitor. This cannot be undone.",
      "parameters": [
        {
          "name": "monitor_id",
          "type": "string",
          "required": true,
          "description": "The monitor id or uid to delete.",
          "enum": null,
          "inferrable": true
        }
      ],
      "auth": null,
      "secrets": [
        "POSTMAN_API_KEY"
      ],
      "secretsInfo": [
        {
          "name": "POSTMAN_API_KEY",
          "type": "api_key"
        }
      ],
      "output": {
        "type": "json",
        "description": "Confirmation that the monitor was deleted."
      },
      "documentationChunks": [],
      "codeExample": {
        "toolName": "Postman.DeleteMonitor",
        "parameters": {
          "monitor_id": {
            "value": "1e6b6cc1-c760-48e0-968f-4bfaeeae9af1",
            "type": "string",
            "required": true
          }
        },
        "requiresAuth": false,
        "tabLabel": "Call the Tool"
      },
      "metadata": {
        "classification": {
          "serviceDomains": []
        },
        "behavior": {
          "operations": [
            "delete"
          ],
          "readOnly": false,
          "destructive": true,
          "idempotent": true,
          "openWorld": true
        },
        "extras": null
      }
    },
    {
      "name": "ForkCollection",
      "qualifiedName": "Postman.ForkCollection",
      "fullyQualifiedName": "Postman.ForkCollection@0.1.0",
      "description": "Fork a collection into a workspace as an independent, editable copy.",
      "parameters": [
        {
          "name": "collection_id",
          "type": "string",
          "required": true,
          "description": "The collection id or uid to fork.",
          "enum": null,
          "inferrable": true
        },
        {
          "name": "label",
          "type": "string",
          "required": true,
          "description": "Label for the fork.",
          "enum": null,
          "inferrable": true
        },
        {
          "name": "workspace_id",
          "type": "string",
          "required": false,
          "description": "Workspace to create the fork in. Leave empty to use your personal (default) workspace; passing it avoids a default-workspace lookup, useful when creating many in a batch.",
          "enum": null,
          "inferrable": true
        }
      ],
      "auth": null,
      "secrets": [
        "POSTMAN_API_KEY"
      ],
      "secretsInfo": [
        {
          "name": "POSTMAN_API_KEY",
          "type": "api_key"
        }
      ],
      "output": {
        "type": "json",
        "description": "The forked copy of the collection."
      },
      "documentationChunks": [],
      "codeExample": {
        "toolName": "Postman.ForkCollection",
        "parameters": {
          "collection_id": {
            "value": "12345678-abcd-1234-efgh-1234567890ab",
            "type": "string",
            "required": true
          },
          "label": {
            "value": "My Feature Branch Fork",
            "type": "string",
            "required": true
          },
          "workspace_id": {
            "value": "87654321-dcba-4321-hgfe-0987654321ba",
            "type": "string",
            "required": false
          }
        },
        "requiresAuth": false,
        "tabLabel": "Call the Tool"
      },
      "metadata": {
        "classification": {
          "serviceDomains": []
        },
        "behavior": {
          "operations": [
            "read",
            "create"
          ],
          "readOnly": false,
          "destructive": false,
          "idempotent": false,
          "openWorld": true
        },
        "extras": null
      }
    },
    {
      "name": "GetApi",
      "qualifiedName": "Postman.GetApi",
      "fullyQualifiedName": "Postman.GetApi@0.1.0",
      "description": "Inspect an API definition, including its name, summary, and attached schemas.",
      "parameters": [
        {
          "name": "api_id",
          "type": "string",
          "required": true,
          "description": "The API definition id.",
          "enum": null,
          "inferrable": true
        }
      ],
      "auth": null,
      "secrets": [
        "POSTMAN_API_KEY"
      ],
      "secretsInfo": [
        {
          "name": "POSTMAN_API_KEY",
          "type": "api_key"
        }
      ],
      "output": {
        "type": "json",
        "description": "The API definition with references to its schemas."
      },
      "documentationChunks": [],
      "codeExample": {
        "toolName": "Postman.GetApi",
        "parameters": {
          "api_id": {
            "value": "a1b2c3d4-e5f6-7890-abcd-ef1234567890",
            "type": "string",
            "required": true
          }
        },
        "requiresAuth": false,
        "tabLabel": "Call the Tool"
      },
      "metadata": {
        "classification": {
          "serviceDomains": []
        },
        "behavior": {
          "operations": [
            "read"
          ],
          "readOnly": true,
          "destructive": false,
          "idempotent": true,
          "openWorld": true
        },
        "extras": null
      }
    },
    {
      "name": "GetApiSchema",
      "qualifiedName": "Postman.GetApiSchema",
      "fullyQualifiedName": "Postman.GetApiSchema@0.1.0",
      "description": "Read an API schema's files and their definition content.",
      "parameters": [
        {
          "name": "api_id",
          "type": "string",
          "required": true,
          "description": "The API definition id.",
          "enum": null,
          "inferrable": true
        },
        {
          "name": "schema_id",
          "type": "string",
          "required": true,
          "description": "The id of the schema to read.",
          "enum": null,
          "inferrable": true
        }
      ],
      "auth": null,
      "secrets": [
        "POSTMAN_API_KEY"
      ],
      "secretsInfo": [
        {
          "name": "POSTMAN_API_KEY",
          "type": "api_key"
        }
      ],
      "output": {
        "type": "json",
        "description": "The schema's files and their definition content."
      },
      "documentationChunks": [],
      "codeExample": {
        "toolName": "Postman.GetApiSchema",
        "parameters": {
          "api_id": {
            "value": "a1b2c3d4-e5f6-7890-abcd-ef1234567890",
            "type": "string",
            "required": true
          },
          "schema_id": {
            "value": "s9f8e7d6-c5b4-3210-fedc-ba9876543210",
            "type": "string",
            "required": true
          }
        },
        "requiresAuth": false,
        "tabLabel": "Call the Tool"
      },
      "metadata": {
        "classification": {
          "serviceDomains": []
        },
        "behavior": {
          "operations": [
            "read"
          ],
          "readOnly": true,
          "destructive": false,
          "idempotent": true,
          "openWorld": true
        },
        "extras": null
      }
    },
    {
      "name": "GetCollection",
      "qualifiedName": "Postman.GetCollection",
      "fullyQualifiedName": "Postman.GetCollection@0.1.0",
      "description": "Inspect a collection and return its variables and a flat tree of its folders and requests.",
      "parameters": [
        {
          "name": "collection_id",
          "type": "string",
          "required": true,
          "description": "The collection id or uid. Prefer the uid for a collection shared by a teammate, whose bare id can be rejected.",
          "enum": null,
          "inferrable": true
        }
      ],
      "auth": null,
      "secrets": [
        "POSTMAN_API_KEY"
      ],
      "secretsInfo": [
        {
          "name": "POSTMAN_API_KEY",
          "type": "api_key"
        }
      ],
      "output": {
        "type": "json",
        "description": "The collection with its folders and requests."
      },
      "documentationChunks": [],
      "codeExample": {
        "toolName": "Postman.GetCollection",
        "parameters": {
          "collection_id": {
            "value": "12345678-abcd-1234-efgh-1234567890ab",
            "type": "string",
            "required": true
          }
        },
        "requiresAuth": false,
        "tabLabel": "Call the Tool"
      },
      "metadata": {
        "classification": {
          "serviceDomains": []
        },
        "behavior": {
          "operations": [
            "read"
          ],
          "readOnly": true,
          "destructive": false,
          "idempotent": true,
          "openWorld": true
        },
        "extras": null
      }
    },
    {
      "name": "GetCollectionOpenapi",
      "qualifiedName": "Postman.GetCollectionOpenapi",
      "fullyQualifiedName": "Postman.GetCollectionOpenapi@0.1.0",
      "description": "Export a collection as an OpenAPI definition.",
      "parameters": [
        {
          "name": "collection_id",
          "type": "string",
          "required": true,
          "description": "The collection id or uid to export.",
          "enum": null,
          "inferrable": true
        }
      ],
      "auth": null,
      "secrets": [
        "POSTMAN_API_KEY"
      ],
      "secretsInfo": [
        {
          "name": "POSTMAN_API_KEY",
          "type": "api_key"
        }
      ],
      "output": {
        "type": "json",
        "description": "The collection exported as an OpenAPI definition."
      },
      "documentationChunks": [],
      "codeExample": {
        "toolName": "Postman.GetCollectionOpenapi",
        "parameters": {
          "collection_id": {
            "value": "12345678-abcd-1234-efgh-567890ijklmn",
            "type": "string",
            "required": true
          }
        },
        "requiresAuth": false,
        "tabLabel": "Call the Tool"
      },
      "metadata": {
        "classification": {
          "serviceDomains": []
        },
        "behavior": {
          "operations": [
            "read"
          ],
          "readOnly": true,
          "destructive": false,
          "idempotent": true,
          "openWorld": true
        },
        "extras": null
      }
    },
    {
      "name": "GetEnvironment",
      "qualifiedName": "Postman.GetEnvironment",
      "fullyQualifiedName": "Postman.GetEnvironment@0.1.0",
      "description": "Inspect an environment and return its variables.",
      "parameters": [
        {
          "name": "environment_id",
          "type": "string",
          "required": true,
          "description": "The environment id or uid. Prefer the uid for an environment shared by a teammate, whose bare id can be rejected.",
          "enum": null,
          "inferrable": true
        }
      ],
      "auth": null,
      "secrets": [
        "POSTMAN_API_KEY"
      ],
      "secretsInfo": [
        {
          "name": "POSTMAN_API_KEY",
          "type": "api_key"
        }
      ],
      "output": {
        "type": "json",
        "description": "The environment and its variables."
      },
      "documentationChunks": [],
      "codeExample": {
        "toolName": "Postman.GetEnvironment",
        "parameters": {
          "environment_id": {
            "value": "6d9a7b3c-1f2e-4a5d-8c0b-2e3f4a5b6c7d",
            "type": "string",
            "required": true
          }
        },
        "requiresAuth": false,
        "tabLabel": "Call the Tool"
      },
      "metadata": {
        "classification": {
          "serviceDomains": []
        },
        "behavior": {
          "operations": [
            "read"
          ],
          "readOnly": true,
          "destructive": false,
          "idempotent": true,
          "openWorld": true
        },
        "extras": null
      }
    },
    {
      "name": "GetMock",
      "qualifiedName": "Postman.GetMock",
      "fullyQualifiedName": "Postman.GetMock@0.1.0",
      "description": "Inspect a mock server, including its public URL and the collection it is based on.",
      "parameters": [
        {
          "name": "mock_id",
          "type": "string",
          "required": true,
          "description": "The mock server id.",
          "enum": null,
          "inferrable": true
        }
      ],
      "auth": null,
      "secrets": [
        "POSTMAN_API_KEY"
      ],
      "secretsInfo": [
        {
          "name": "POSTMAN_API_KEY",
          "type": "api_key"
        }
      ],
      "output": {
        "type": "json",
        "description": "The mock server, its public URL, and its linked collection."
      },
      "documentationChunks": [],
      "codeExample": {
        "toolName": "Postman.GetMock",
        "parameters": {
          "mock_id": {
            "value": "a1b2c3d4-e5f6-7890-abcd-ef1234567890",
            "type": "string",
            "required": true
          }
        },
        "requiresAuth": false,
        "tabLabel": "Call the Tool"
      },
      "metadata": {
        "classification": {
          "serviceDomains": []
        },
        "behavior": {
          "operations": [
            "read"
          ],
          "readOnly": true,
          "destructive": false,
          "idempotent": true,
          "openWorld": true
        },
        "extras": null
      }
    },
    {
      "name": "GetMonitor",
      "qualifiedName": "Postman.GetMonitor",
      "fullyQualifiedName": "Postman.GetMonitor@0.1.0",
      "description": "Inspect a monitor, including its run schedule and most recent run result.",
      "parameters": [
        {
          "name": "monitor_id",
          "type": "string",
          "required": true,
          "description": "The monitor id or uid.",
          "enum": null,
          "inferrable": true
        }
      ],
      "auth": null,
      "secrets": [
        "POSTMAN_API_KEY"
      ],
      "secretsInfo": [
        {
          "name": "POSTMAN_API_KEY",
          "type": "api_key"
        }
      ],
      "output": {
        "type": "json",
        "description": "The monitor with its schedule and most recent run outcome."
      },
      "documentationChunks": [],
      "codeExample": {
        "toolName": "Postman.GetMonitor",
        "parameters": {
          "monitor_id": {
            "value": "1e6b6cc1-c760-48e0-968f-4bfaeeae9af1",
            "type": "string",
            "required": true
          }
        },
        "requiresAuth": false,
        "tabLabel": "Call the Tool"
      },
      "metadata": {
        "classification": {
          "serviceDomains": []
        },
        "behavior": {
          "operations": [
            "read"
          ],
          "readOnly": true,
          "destructive": false,
          "idempotent": true,
          "openWorld": true
        },
        "extras": null
      }
    },
    {
      "name": "GetWorkspace",
      "qualifiedName": "Postman.GetWorkspace",
      "fullyQualifiedName": "Postman.GetWorkspace@0.1.0",
      "description": "Inspect a workspace and list the collections, environments, mocks, and monitors in it.",
      "parameters": [
        {
          "name": "workspace_id",
          "type": "string",
          "required": true,
          "description": "The unique workspace identifier.",
          "enum": null,
          "inferrable": true
        }
      ],
      "auth": null,
      "secrets": [
        "POSTMAN_API_KEY"
      ],
      "secretsInfo": [
        {
          "name": "POSTMAN_API_KEY",
          "type": "api_key"
        }
      ],
      "output": {
        "type": "json",
        "description": "The workspace and the resources it contains."
      },
      "documentationChunks": [],
      "codeExample": {
        "toolName": "Postman.GetWorkspace",
        "parameters": {
          "workspace_id": {
            "value": "1f0df51a-8658-4ee8-a2a1-d2567dfa09a9",
            "type": "string",
            "required": true
          }
        },
        "requiresAuth": false,
        "tabLabel": "Call the Tool"
      },
      "metadata": {
        "classification": {
          "serviceDomains": []
        },
        "behavior": {
          "operations": [
            "read"
          ],
          "readOnly": true,
          "destructive": false,
          "idempotent": true,
          "openWorld": true
        },
        "extras": null
      }
    },
    {
      "name": "ListApis",
      "qualifiedName": "Postman.ListApis",
      "fullyQualifiedName": "Postman.ListApis@0.1.0",
      "description": "List the API definitions in a workspace.",
      "parameters": [
        {
          "name": "workspace_id",
          "type": "string",
          "required": true,
          "description": "The workspace whose API definitions to list.",
          "enum": null,
          "inferrable": true
        },
        {
          "name": "limit",
          "type": "integer",
          "required": false,
          "description": "Maximum results to return (1-100). Defaults to 20.",
          "enum": null,
          "inferrable": true
        },
        {
          "name": "offset",
          "type": "integer",
          "required": false,
          "description": "0-indexed starting position. Defaults to 0. Paging to a deep offset re-scans the preceding results on this endpoint, so prefer a modest limit over paging far.",
          "enum": null,
          "inferrable": true
        }
      ],
      "auth": null,
      "secrets": [
        "POSTMAN_API_KEY"
      ],
      "secretsInfo": [
        {
          "name": "POSTMAN_API_KEY",
          "type": "api_key"
        }
      ],
      "output": {
        "type": "json",
        "description": "The API definitions in the workspace."
      },
      "documentationChunks": [],
      "codeExample": {
        "toolName": "Postman.ListApis",
        "parameters": {
          "workspace_id": {
            "value": "1f0df51a-8658-4ee8-a2a1-d2567dfa09a9",
            "type": "string",
            "required": true
          },
          "limit": {
            "value": 25,
            "type": "integer",
            "required": false
          },
          "offset": {
            "value": 0,
            "type": "integer",
            "required": false
          }
        },
        "requiresAuth": false,
        "tabLabel": "Call the Tool"
      },
      "metadata": {
        "classification": {
          "serviceDomains": []
        },
        "behavior": {
          "operations": [
            "read"
          ],
          "readOnly": true,
          "destructive": false,
          "idempotent": true,
          "openWorld": true
        },
        "extras": null
      }
    },
    {
      "name": "ListCollections",
      "qualifiedName": "Postman.ListCollections",
      "fullyQualifiedName": "Postman.ListCollections@0.1.0",
      "description": "List collections, optionally scoped to a workspace and filtered by name.\n\nWithout a workspace this returns the collections the API key can access: those you own or\nhave subscribed to. A collection another team member created in a shared workspace may not\nappear here until it is subscribed to; use get_workspace to see everything a workspace holds.",
      "parameters": [
        {
          "name": "workspace_id",
          "type": "string",
          "required": false,
          "description": "Scope results to this workspace. Leave empty to span all accessible workspaces.",
          "enum": null,
          "inferrable": true
        },
        {
          "name": "name",
          "type": "string",
          "required": false,
          "description": "Filter to collections whose name contains this text. Leave empty for no filter.",
          "enum": null,
          "inferrable": true
        },
        {
          "name": "limit",
          "type": "integer",
          "required": false,
          "description": "Maximum results to return (1-100). Defaults to 20.",
          "enum": null,
          "inferrable": true
        },
        {
          "name": "offset",
          "type": "integer",
          "required": false,
          "description": "0-indexed starting position. Defaults to 0.",
          "enum": null,
          "inferrable": true
        }
      ],
      "auth": null,
      "secrets": [
        "POSTMAN_API_KEY"
      ],
      "secretsInfo": [
        {
          "name": "POSTMAN_API_KEY",
          "type": "api_key"
        }
      ],
      "output": {
        "type": "json",
        "description": "The collections matching the filters."
      },
      "documentationChunks": [],
      "codeExample": {
        "toolName": "Postman.ListCollections",
        "parameters": {
          "workspace_id": {
            "value": "1f0df51a-8658-4ee8-a2a1-d2567dfa09a9",
            "type": "string",
            "required": false
          },
          "name": {
            "value": "Payment API",
            "type": "string",
            "required": false
          },
          "limit": {
            "value": 25,
            "type": "integer",
            "required": false
          },
          "offset": {
            "value": 0,
            "type": "integer",
            "required": false
          }
        },
        "requiresAuth": false,
        "tabLabel": "Call the Tool"
      },
      "metadata": {
        "classification": {
          "serviceDomains": []
        },
        "behavior": {
          "operations": [
            "read"
          ],
          "readOnly": true,
          "destructive": false,
          "idempotent": true,
          "openWorld": true
        },
        "extras": null
      }
    },
    {
      "name": "ListEnvironments",
      "qualifiedName": "Postman.ListEnvironments",
      "fullyQualifiedName": "Postman.ListEnvironments@0.1.0",
      "description": "List environments, optionally scoped to a workspace and filtered by name.",
      "parameters": [
        {
          "name": "workspace_id",
          "type": "string",
          "required": false,
          "description": "Scope results to this workspace. Leave empty to span all accessible workspaces.",
          "enum": null,
          "inferrable": true
        },
        {
          "name": "name",
          "type": "string",
          "required": false,
          "description": "Filter to environments whose name contains this text. Leave empty for no filter.",
          "enum": null,
          "inferrable": true
        },
        {
          "name": "limit",
          "type": "integer",
          "required": false,
          "description": "Maximum results to return (1-100). Defaults to 20.",
          "enum": null,
          "inferrable": true
        },
        {
          "name": "offset",
          "type": "integer",
          "required": false,
          "description": "0-indexed starting position. Defaults to 0.",
          "enum": null,
          "inferrable": true
        }
      ],
      "auth": null,
      "secrets": [
        "POSTMAN_API_KEY"
      ],
      "secretsInfo": [
        {
          "name": "POSTMAN_API_KEY",
          "type": "api_key"
        }
      ],
      "output": {
        "type": "json",
        "description": "The environments matching the filters."
      },
      "documentationChunks": [],
      "codeExample": {
        "toolName": "Postman.ListEnvironments",
        "parameters": {
          "workspace_id": {
            "value": "1f0df51a-8658-4ee8-a2a1-d2567dfa09a7",
            "type": "string",
            "required": false
          },
          "name": {
            "value": "production",
            "type": "string",
            "required": false
          },
          "limit": {
            "value": 25,
            "type": "integer",
            "required": false
          },
          "offset": {
            "value": 0,
            "type": "integer",
            "required": false
          }
        },
        "requiresAuth": false,
        "tabLabel": "Call the Tool"
      },
      "metadata": {
        "classification": {
          "serviceDomains": []
        },
        "behavior": {
          "operations": [
            "read"
          ],
          "readOnly": true,
          "destructive": false,
          "idempotent": true,
          "openWorld": true
        },
        "extras": null
      }
    },
    {
      "name": "ListMocks",
      "qualifiedName": "Postman.ListMocks",
      "fullyQualifiedName": "Postman.ListMocks@0.1.0",
      "description": "List mock servers, optionally scoped to a workspace and filtered by name.",
      "parameters": [
        {
          "name": "workspace_id",
          "type": "string",
          "required": false,
          "description": "Scope results to this workspace. Leave empty to span all accessible workspaces.",
          "enum": null,
          "inferrable": true
        },
        {
          "name": "name",
          "type": "string",
          "required": false,
          "description": "Filter to mock servers whose name contains this text. Leave empty for no filter.",
          "enum": null,
          "inferrable": true
        },
        {
          "name": "limit",
          "type": "integer",
          "required": false,
          "description": "Maximum results to return (1-100). Defaults to 20.",
          "enum": null,
          "inferrable": true
        },
        {
          "name": "offset",
          "type": "integer",
          "required": false,
          "description": "0-indexed starting position. Defaults to 0.",
          "enum": null,
          "inferrable": true
        }
      ],
      "auth": null,
      "secrets": [
        "POSTMAN_API_KEY"
      ],
      "secretsInfo": [
        {
          "name": "POSTMAN_API_KEY",
          "type": "api_key"
        }
      ],
      "output": {
        "type": "json",
        "description": "The mock servers matching the filters."
      },
      "documentationChunks": [],
      "codeExample": {
        "toolName": "Postman.ListMocks",
        "parameters": {
          "workspace_id": {
            "value": "1f0df51a-8658-4ee8-a2a1-d2567dfa09a9",
            "type": "string",
            "required": false
          },
          "name": {
            "value": "staging-mock",
            "type": "string",
            "required": false
          },
          "limit": {
            "value": 25,
            "type": "integer",
            "required": false
          },
          "offset": {
            "value": 0,
            "type": "integer",
            "required": false
          }
        },
        "requiresAuth": false,
        "tabLabel": "Call the Tool"
      },
      "metadata": {
        "classification": {
          "serviceDomains": []
        },
        "behavior": {
          "operations": [
            "read"
          ],
          "readOnly": true,
          "destructive": false,
          "idempotent": true,
          "openWorld": true
        },
        "extras": null
      }
    },
    {
      "name": "ListMonitors",
      "qualifiedName": "Postman.ListMonitors",
      "fullyQualifiedName": "Postman.ListMonitors@0.1.0",
      "description": "List monitors, optionally scoped to a workspace.",
      "parameters": [
        {
          "name": "workspace_id",
          "type": "string",
          "required": false,
          "description": "Scope results to this workspace. Leave empty to span all accessible workspaces.",
          "enum": null,
          "inferrable": true
        },
        {
          "name": "limit",
          "type": "integer",
          "required": false,
          "description": "Maximum results to return (1-100). Defaults to 20.",
          "enum": null,
          "inferrable": true
        },
        {
          "name": "offset",
          "type": "integer",
          "required": false,
          "description": "0-indexed starting position. Defaults to 0.",
          "enum": null,
          "inferrable": true
        }
      ],
      "auth": null,
      "secrets": [
        "POSTMAN_API_KEY"
      ],
      "secretsInfo": [
        {
          "name": "POSTMAN_API_KEY",
          "type": "api_key"
        }
      ],
      "output": {
        "type": "json",
        "description": "The monitors matching the filters."
      },
      "documentationChunks": [],
      "codeExample": {
        "toolName": "Postman.ListMonitors",
        "parameters": {
          "workspace_id": {
            "value": "1f0df51a-8658-4ee8-a2a1-d2567dfa09a9",
            "type": "string",
            "required": false
          },
          "limit": {
            "value": 25,
            "type": "integer",
            "required": false
          },
          "offset": {
            "value": 0,
            "type": "integer",
            "required": false
          }
        },
        "requiresAuth": false,
        "tabLabel": "Call the Tool"
      },
      "metadata": {
        "classification": {
          "serviceDomains": []
        },
        "behavior": {
          "operations": [
            "read"
          ],
          "readOnly": true,
          "destructive": false,
          "idempotent": true,
          "openWorld": true
        },
        "extras": null
      }
    },
    {
      "name": "ListWorkspaces",
      "qualifiedName": "Postman.ListWorkspaces",
      "fullyQualifiedName": "Postman.ListWorkspaces@0.1.0",
      "description": "List the workspaces the API key can access, optionally filtered by type.",
      "parameters": [
        {
          "name": "workspace_type",
          "type": "string",
          "required": false,
          "description": "Filter to one workspace type. Defaults to ALL (no filter).",
          "enum": [
            "all",
            "personal",
            "team",
            "private",
            "public",
            "partner"
          ],
          "inferrable": true
        },
        {
          "name": "limit",
          "type": "integer",
          "required": false,
          "description": "Maximum results to return (1-100). Defaults to 20.",
          "enum": null,
          "inferrable": true
        },
        {
          "name": "offset",
          "type": "integer",
          "required": false,
          "description": "0-indexed starting position. Defaults to 0.",
          "enum": null,
          "inferrable": true
        }
      ],
      "auth": null,
      "secrets": [
        "POSTMAN_API_KEY"
      ],
      "secretsInfo": [
        {
          "name": "POSTMAN_API_KEY",
          "type": "api_key"
        }
      ],
      "output": {
        "type": "json",
        "description": "The workspaces accessible to the API key."
      },
      "documentationChunks": [],
      "codeExample": {
        "toolName": "Postman.ListWorkspaces",
        "parameters": {
          "workspace_type": {
            "value": "personal",
            "type": "string",
            "required": false
          },
          "limit": {
            "value": 25,
            "type": "integer",
            "required": false
          },
          "offset": {
            "value": 0,
            "type": "integer",
            "required": false
          }
        },
        "requiresAuth": false,
        "tabLabel": "Call the Tool"
      },
      "metadata": {
        "classification": {
          "serviceDomains": []
        },
        "behavior": {
          "operations": [
            "read"
          ],
          "readOnly": true,
          "destructive": false,
          "idempotent": true,
          "openWorld": true
        },
        "extras": null
      }
    },
    {
      "name": "RunMonitor",
      "qualifiedName": "Postman.RunMonitor",
      "fullyQualifiedName": "Postman.RunMonitor@0.1.0",
      "description": "Trigger a monitor to run now and return its pass/fail results.\n\nThe run is synchronous: Postman holds the connection until the collection finishes. A run\nthat outlasts the tool's bounded wait returns ``timed_out=true`` while still executing\nupstream; read the outcome from get_monitor's last-run fields rather than retrying.",
      "parameters": [
        {
          "name": "monitor_id",
          "type": "string",
          "required": true,
          "description": "The monitor id or uid to run.",
          "enum": null,
          "inferrable": true
        }
      ],
      "auth": null,
      "secrets": [
        "POSTMAN_API_KEY"
      ],
      "secretsInfo": [
        {
          "name": "POSTMAN_API_KEY",
          "type": "api_key"
        }
      ],
      "output": {
        "type": "json",
        "description": "The pass/fail outcome of the monitor run."
      },
      "documentationChunks": [],
      "codeExample": {
        "toolName": "Postman.RunMonitor",
        "parameters": {
          "monitor_id": {
            "value": "1e6b8c2d-3f4a-5e7b-8c9d-0e1f2a3b4c5d",
            "type": "string",
            "required": true
          }
        },
        "requiresAuth": false,
        "tabLabel": "Call the Tool"
      },
      "metadata": {
        "classification": {
          "serviceDomains": []
        },
        "behavior": {
          "operations": [
            "opaque"
          ],
          "readOnly": false,
          "destructive": false,
          "idempotent": false,
          "openWorld": true
        },
        "extras": null
      }
    },
    {
      "name": "SaveCollection",
      "qualifiedName": "Postman.SaveCollection",
      "fullyQualifiedName": "Postman.SaveCollection@0.1.0",
      "description": "Create a new collection, or update an existing one when collection_id is provided.",
      "parameters": [
        {
          "name": "collection_id",
          "type": "string",
          "required": false,
          "description": "Id or uid of the collection to update. Omit to create a new collection instead.",
          "enum": null,
          "inferrable": true
        },
        {
          "name": "name",
          "type": "string",
          "required": false,
          "description": "When creating (no collection_id), the new collection's name. When updating, providing this renames the collection; omitting it leaves the name unchanged.",
          "enum": null,
          "inferrable": true
        },
        {
          "name": "description",
          "type": "string",
          "required": false,
          "description": "When creating, sets the description. When updating, providing this changes it; omitting it leaves the description unchanged.",
          "enum": null,
          "inferrable": true
        },
        {
          "name": "workspace_id",
          "type": "string",
          "required": false,
          "description": "When creating, the workspace to create the collection in; leave empty to use your personal (default) workspace (passing it avoids a default-workspace lookup, which matters when creating many in a batch). Ignored when updating an existing collection.",
          "enum": null,
          "inferrable": true
        }
      ],
      "auth": null,
      "secrets": [
        "POSTMAN_API_KEY"
      ],
      "secretsInfo": [
        {
          "name": "POSTMAN_API_KEY",
          "type": "api_key"
        }
      ],
      "output": {
        "type": "json",
        "description": "The created or updated collection."
      },
      "documentationChunks": [],
      "codeExample": {
        "toolName": "Postman.SaveCollection",
        "parameters": {
          "collection_id": {
            "value": "12345678-abcd-1234-efgh-abcdef123456",
            "type": "string",
            "required": false
          },
          "name": {
            "value": "My API Test Collection",
            "type": "string",
            "required": false
          },
          "description": {
            "value": "A collection containing example API requests for testing the user authentication flow.",
            "type": "string",
            "required": false
          },
          "workspace_id": {
            "value": "87654321-dcba-4321-hgfe-fedcba654321",
            "type": "string",
            "required": false
          }
        },
        "requiresAuth": false,
        "tabLabel": "Call the Tool"
      },
      "metadata": {
        "classification": {
          "serviceDomains": []
        },
        "behavior": {
          "operations": [
            "create",
            "update"
          ],
          "readOnly": false,
          "destructive": false,
          "idempotent": false,
          "openWorld": true
        },
        "extras": null
      }
    },
    {
      "name": "SaveEnvironment",
      "qualifiedName": "Postman.SaveEnvironment",
      "fullyQualifiedName": "Postman.SaveEnvironment@0.1.0",
      "description": "Create a new environment, or update an existing one when environment_id is provided.",
      "parameters": [
        {
          "name": "environment_id",
          "type": "string",
          "required": false,
          "description": "Id or uid of the environment to update. Omit to create a new environment instead.",
          "enum": null,
          "inferrable": true
        },
        {
          "name": "name",
          "type": "string",
          "required": false,
          "description": "When creating (no environment_id), the new environment's name. When updating, providing this renames it; omitting it leaves the name unchanged.",
          "enum": null,
          "inferrable": true
        },
        {
          "name": "values",
          "type": "array",
          "innerType": "json",
          "required": false,
          "description": "The environment's variables. When creating, seeds them (omit or pass an empty list for none). When updating, providing this replaces the full set; omitting it leaves the existing variables unchanged.",
          "enum": null,
          "inferrable": true
        },
        {
          "name": "workspace_id",
          "type": "string",
          "required": false,
          "description": "When creating, the workspace to create the environment in; leave empty to use your personal (default) workspace (passing it avoids a default-workspace lookup, which matters when creating many in a batch). Ignored when updating an existing environment.",
          "enum": null,
          "inferrable": true
        }
      ],
      "auth": null,
      "secrets": [
        "POSTMAN_API_KEY"
      ],
      "secretsInfo": [
        {
          "name": "POSTMAN_API_KEY",
          "type": "api_key"
        }
      ],
      "output": {
        "type": "json",
        "description": "The created or updated environment."
      },
      "documentationChunks": [],
      "codeExample": {
        "toolName": "Postman.SaveEnvironment",
        "parameters": {
          "environment_id": {
            "value": "a1b2c3d4-e5f6-7890-abcd-ef1234567890",
            "type": "string",
            "required": false
          },
          "name": {
            "value": "Production Environment",
            "type": "string",
            "required": false
          },
          "values": {
            "value": [
              {
                "key": "BASE_URL",
                "value": "https://api.example.com",
                "enabled": true,
                "type": "default"
              },
              {
                "key": "API_VERSION",
                "value": "v2",
                "enabled": true,
                "type": "default"
              },
              {
                "key": "TIMEOUT",
                "value": "30000",
                "enabled": true,
                "type": "default"
              }
            ],
            "type": "array",
            "required": false
          },
          "workspace_id": {
            "value": "9f8e7d6c-5b4a-3210-fedc-ba9876543210",
            "type": "string",
            "required": false
          }
        },
        "requiresAuth": false,
        "tabLabel": "Call the Tool"
      },
      "metadata": {
        "classification": {
          "serviceDomains": []
        },
        "behavior": {
          "operations": [
            "create",
            "update"
          ],
          "readOnly": false,
          "destructive": true,
          "idempotent": false,
          "openWorld": true
        },
        "extras": null
      }
    },
    {
      "name": "UpdateCollectionItem",
      "qualifiedName": "Postman.UpdateCollectionItem",
      "fullyQualifiedName": "Postman.UpdateCollectionItem@0.1.0",
      "description": "Rename a folder or request, or change a request's method or URL.",
      "parameters": [
        {
          "name": "collection_id",
          "type": "string",
          "required": true,
          "description": "The collection id or uid containing the item.",
          "enum": null,
          "inferrable": true
        },
        {
          "name": "item_id",
          "type": "string",
          "required": true,
          "description": "Id of the folder or request to update.",
          "enum": null,
          "inferrable": true
        },
        {
          "name": "item_type",
          "type": "string",
          "required": true,
          "description": "Whether the item is a folder or a request.",
          "enum": [
            "folder",
            "request"
          ],
          "inferrable": true
        },
        {
          "name": "name",
          "type": "string",
          "required": false,
          "description": "New name. Providing this renames the item; omitting it leaves the name unchanged.",
          "enum": null,
          "inferrable": true
        },
        {
          "name": "description",
          "type": "string",
          "required": false,
          "description": "New description. Providing this changes it; omitting it leaves it unchanged.",
          "enum": null,
          "inferrable": true
        },
        {
          "name": "http_method",
          "type": "string",
          "required": false,
          "description": "New HTTP method (requests only). Omitting it leaves the method unchanged.",
          "enum": [
            "GET",
            "POST",
            "PUT",
            "PATCH",
            "DELETE",
            "HEAD",
            "OPTIONS"
          ],
          "inferrable": true
        },
        {
          "name": "url",
          "type": "string",
          "required": false,
          "description": "New request URL (requests only). Omitting it leaves the URL unchanged.",
          "enum": null,
          "inferrable": true
        }
      ],
      "auth": null,
      "secrets": [
        "POSTMAN_API_KEY"
      ],
      "secretsInfo": [
        {
          "name": "POSTMAN_API_KEY",
          "type": "api_key"
        }
      ],
      "output": {
        "type": "json",
        "description": "The updated folder or request."
      },
      "documentationChunks": [],
      "codeExample": {
        "toolName": "Postman.UpdateCollectionItem",
        "parameters": {
          "collection_id": {
            "value": "12345678-abcd-1234-efgh-abcdef123456",
            "type": "string",
            "required": true
          },
          "item_id": {
            "value": "a1b2c3d4-e5f6-7890-abcd-ef1234567890",
            "type": "string",
            "required": true
          },
          "item_type": {
            "value": "request",
            "type": "string",
            "required": true
          },
          "name": {
            "value": "Get User Profile",
            "type": "string",
            "required": false
          },
          "description": {
            "value": "Fetches the profile details of a specific user by ID.",
            "type": "string",
            "required": false
          },
          "http_method": {
            "value": "GET",
            "type": "string",
            "required": false
          },
          "url": {
            "value": "https://api.example.com/v1/users/{{userId}}/profile",
            "type": "string",
            "required": false
          }
        },
        "requiresAuth": false,
        "tabLabel": "Call the Tool"
      },
      "metadata": {
        "classification": {
          "serviceDomains": []
        },
        "behavior": {
          "operations": [
            "update"
          ],
          "readOnly": false,
          "destructive": false,
          "idempotent": false,
          "openWorld": true
        },
        "extras": null
      }
    },
    {
      "name": "UpdateEnvironmentVariables",
      "qualifiedName": "Postman.UpdateEnvironmentVariables",
      "fullyQualifiedName": "Postman.UpdateEnvironmentVariables@0.1.0",
      "description": "Set or remove individual environment variables without resending the whole variable set.",
      "parameters": [
        {
          "name": "environment_id",
          "type": "string",
          "required": true,
          "description": "Id or uid of the environment to edit.",
          "enum": null,
          "inferrable": true
        },
        {
          "name": "set_variables",
          "type": "array",
          "innerType": "json",
          "required": false,
          "description": "Variables to add or change; each one upserts by key, replacing that variable's value while leaving every other variable untouched. Omit for no additions or changes.",
          "enum": null,
          "inferrable": true
        },
        {
          "name": "unset_keys",
          "type": "array",
          "innerType": "string",
          "required": false,
          "description": "Keys of variables to remove. Keys that are not present are ignored. Omit to remove nothing.",
          "enum": null,
          "inferrable": true
        }
      ],
      "auth": null,
      "secrets": [
        "POSTMAN_API_KEY"
      ],
      "secretsInfo": [
        {
          "name": "POSTMAN_API_KEY",
          "type": "api_key"
        }
      ],
      "output": {
        "type": "json",
        "description": "The environment with its updated variables."
      },
      "documentationChunks": [],
      "codeExample": {
        "toolName": "Postman.UpdateEnvironmentVariables",
        "parameters": {
          "environment_id": {
            "value": "a1b2c3d4-e5f6-7890-abcd-ef1234567890",
            "type": "string",
            "required": true
          },
          "set_variables": {
            "value": [
              {
                "key": "BASE_URL",
                "value": "https://api.example.com/v1",
                "type": "default",
                "enabled": true
              },
              {
                "key": "AUTH_TOKEN",
                "value": "eyJhbGciOiJIUzI1NiIsInR5cCI6IkpXVCJ9.example",
                "type": "secret",
                "enabled": true
              },
              {
                "key": "TIMEOUT",
                "value": "3000",
                "type": "default",
                "enabled": true
              }
            ],
            "type": "array",
            "required": false
          },
          "unset_keys": {
            "value": [
              "DEPRECATED_ENDPOINT",
              "OLD_API_KEY",
              "STAGING_URL"
            ],
            "type": "array",
            "required": false
          }
        },
        "requiresAuth": false,
        "tabLabel": "Call the Tool"
      },
      "metadata": {
        "classification": {
          "serviceDomains": []
        },
        "behavior": {
          "operations": [
            "update"
          ],
          "readOnly": false,
          "destructive": true,
          "idempotent": true,
          "openWorld": true
        },
        "extras": null
      }
    },
    {
      "name": "WhoAmI",
      "qualifiedName": "Postman.WhoAmI",
      "fullyQualifiedName": "Postman.WhoAmI@0.1.0",
      "description": "Identify the Postman account the configured API key belongs to and its plan usage.",
      "parameters": [],
      "auth": null,
      "secrets": [
        "POSTMAN_API_KEY"
      ],
      "secretsInfo": [
        {
          "name": "POSTMAN_API_KEY",
          "type": "api_key"
        }
      ],
      "output": {
        "type": "json",
        "description": "The Postman account the API key belongs to."
      },
      "documentationChunks": [],
      "codeExample": {
        "toolName": "Postman.WhoAmI",
        "parameters": {},
        "requiresAuth": false,
        "tabLabel": "Call the Tool"
      },
      "metadata": {
        "classification": {
          "serviceDomains": []
        },
        "behavior": {
          "operations": [
            "read"
          ],
          "readOnly": true,
          "destructive": false,
          "idempotent": true,
          "openWorld": true
        },
        "extras": null
      }
    }
  ],
  "documentationChunks": [],
  "customImports": [],
  "subPages": [],
  "generatedAt": "2026-07-16T11:38:53.694Z",
  "summary": "The Postman toolkit lets Arcade agents interact with the [Postman API](https://www.postman.com/) to manage collections, environments, mock servers, monitors, workspaces, and API definitions programmatically.\n\n## Capabilities\n\n- **Collection management** — create, inspect, export (OpenAPI), fork, save, and permanently delete collections; add, update, and delete folders and requests within a collection.\n- **Environment management** — create, inspect, update individual variables, and delete environments.\n- **Mock servers** — create mock servers backed by a collection, inspect them (including their public URL), and delete them.\n- **Monitors** — create scheduled collection monitors, inspect run history and schedules, trigger on-demand runs with pass/fail results, and delete monitors.\n- **Workspace and API discovery** — list and inspect workspaces, list collections/environments/mocks/monitors scoped to a workspace, list and inspect API definitions and their schemas.\n- **Account introspection** — identify the authenticated Postman account and its plan usage.\n\n## Secrets\n\n`POSTMAN_API_KEY` — A Postman API key that authenticates every request made on behalf of a Postman account. To obtain one:\n1. Log in to [Postman](https://www.postman.com/) and open **Settings → API keys** (direct link: [https://web.postman.co/settings/me/api-keys](https://web.postman.co/settings/me/api-keys)).\n2. Click **Generate API Key**, give it a descriptive name, and copy the value immediately — it is shown only once.\n3. The key inherits the permissions of the account that created it. For team workspaces, ensure the account has access to the workspaces and resources the toolkit needs to read or modify.\n4. Postman's [API key documentation](https://learning.postman.com/docs/developer/postman-api/authentication/) describes key scopes, rotation, and revocation.\n\nStore the key as an Arcade secret. See the [Arcade secrets guide](https://docs.arcade.dev/en/guides/create-tools/tool-basics/create-tool-secrets) for configuration instructions, and manage your secrets at [https://api.arcade.dev/dashboard/auth/secrets](https://api.arcade.dev/dashboard/auth/secrets)."
}